er/__init__.py
er/__main__.py
er/engine.py
er-0.2.dist-info/DESCRIPTION.rst
er-0.2.dist-info/METADATA
er-0.2.dist-info/RECORD
er-0.2.dist-info/WHEEL
er-0.2.dist-info/entry_points.txt
er-0.2.dist-info/metadata.json
er-0.2.dist-info/top_level.txt
er-0.2.dist-info/zip-safe
