Metadata-Version: 1.1
Name: er
Version: 0.2
Summary: Generate data that matches a given regular expression.
Home-page: https://github.com/simon-engledew/python-er
Author: Simon Engledew
Author-email: simon@engledew.com
License: MIT
Keywords: re,test,testing,data,fake,regular expression
Platform: UNKNOWN
Classifier: Development Status :: 1 - Planning
Classifier: Operating System :: OS Independent
Classifier: Programming Language :: Python
Classifier: Programming Language :: Python :: 2.7
Classifier: Programming Language :: Python :: 3
Classifier: Programming Language :: Python :: 3.0
Classifier: Programming Language :: Python :: 3.1
Classifier: Programming Language :: Python :: 3.2
Classifier: Programming Language :: Python :: 3.3
Classifier: Programming Language :: Python :: 3.4
Classifier: Programming Language :: Python :: 3.5
Classifier: Programming Language :: Python :: 3.6
